odysseus/__init__.py
odysseus/models.py
odysseus/odysseus.py
odysseus-0.1.6.dist-info/licenses/LICENSE
odysseus-0.1.6.dist-info/METADATA
odysseus-0.1.6.dist-info/WHEEL
odysseus-0.1.6.dist-info/top_level.txt
odysseus-0.1.6.dist-info/RECORD
