Metadata-Version: 2.4
Name: odysseus
Version: 0.1.6
Summary: A client for CodeTitans Odysseus Logging Platform.
Author-email: Paweł Hofman <pawel@codetitans.pl>
License: Copyright (c) 2018 The Python Packaging Authority
Project-URL: Homepage, https://github.com/codetitans/odysseus-py
Project-URL: Issues, https://github.com/codetitans/odysseus-py/issues
Keywords: logs,logging,Odysseus
Classifier: Programming Language :: Python :: 3
Classifier: Operating System :: OS Independent
Requires-Python: >=3.8
License-File: LICENSE
Requires-Dist: requests<3.0,>=2.32.3
Requires-Dist: tzlocal<6.0,>=5.2
Dynamic: license-file
